fhir_data_generator/__init__.py
fhir_data_generator/iclaim/claim.py
fhir_data_generator/iclaim/coverage.py
fhir_data_generator/iclaim/observation.py
fhir_data_generator/iclaim/patient.py
fhir_data_generator/imri/care_plan.py
fhir_data_generator/imri/composition.py
fhir_data_generator/imri/condition.py
fhir_data_generator/imri/document_reference.py
fhir_data_generator/imri/encounter.py
fhir_data_generator/imri/imaging_study.py
fhir_data_generator/imri/location.py
fhir_data_generator/observation/observation.py
fhir_data_generator/patient/patient.py
fhir_data_generator/physical_activity/care_plan.py
fhir_data_generator/physical_activity/condition_e.py
fhir_data_generator/physical_activity/goal.py
fhir_data_generator/physical_activity/observation.py
fhir_data_generator/physical_activity/organization_h.py
fhir_data_generator/physical_activity/organization_s.py
fhir_data_generator/physical_activity/patient_ex.py
fhir_data_generator/physical_activity/patient_tw.py
fhir_data_generator/physical_activity/practitioner.py
fhir_data_generator/physical_activity/service_request.py
fhir_data_generator/py.typed
fhir_data_generator/simple_client/keycloak_authorization_code.py
fhir_data_generator/simple_client/keycloak_client_credentials.py
fhir_data_generator/simple_client/keycloak_verify_token.py
fhir_data_generator/simple_client/simple_client.py
fhir_data_generator/tw_core_ig/allergyintolerance/allergyintolerance.py
fhir_data_generator/tw_core_ig/composition/composition.py
fhir_data_generator/tw_core_ig/condition/condition.py
fhir_data_generator/tw_core_ig/diagnostic_report/diagnostic_report.py
fhir_data_generator/tw_core_ig/document_reference/document_reference.py
fhir_data_generator/tw_core_ig/encounter/encounter.py
fhir_data_generator/tw_core_ig/imaging_study/imaging_study.py
fhir_data_generator/tw_core_ig/location/location.py
fhir_data_generator/tw_core_ig/media/media.py
fhir_data_generator/tw_core_ig/medication/medication.py
fhir_data_generator-1.7.0.dist-info/LICENSE
fhir_data_generator-1.7.0.dist-info/METADATA
fhir_data_generator-1.7.0.dist-info/WHEEL
fhir_data_generator-1.7.0.dist-info/RECORD
